<?xml version="1.0" encoding="UTF-8" standalone="yes"?>
<school>
    <professor id="0253">
        <name>TUedNUNU</name>
        <birthDate>9/5/1993</birthDate>
        <telephone>44383710</telephone>
        <address>tLqZVFZtISjACpIs</address>
        <students>8316</students>
    </professor>
    <professor id="8309">
        <name>duQmilPm</name>
        <birthDate>27/7/2011</birthDate>
        <telephone>74094019</telephone>
        <address>QEBesygSRQeGxItP</address>
        <students>4198</students>
    </professor>
    <professor id="0209">
        <name>dpKBacIU</name>
        <birthDate>1/10/1989</birthDate>
        <telephone>28407162</telephone>
        <address>UjsWhhLhkcicMXag</address>
    </professor>
    <professor id="8194">
        <name>oHRxKaLp</name>
        <birthDate>31/7/1999</birthDate>
        <telephone>89244291</telephone>
        <address>RTnyBCNxSdSHFIHX</address>
        <students>6583</students>
    </professor>
    <professor id="9292">
        <name>fNLvEcma</name>
        <birthDate>18/8/2012</birthDate>
        <telephone>92076892</telephone>
        <address>KOTaUohuRAuWgBGu</address>
        <students>7541</students>
        <students>6935</students>
    </professor>
    <professor id="7136">
        <name>jPGvTqPR</name>
        <birthDate>22/12/1975</birthDate>
        <telephone>61871391</telephone>
        <address>PYhQHRYhzHeNuDhj</address>
        <students>4848</students>
    </professor>
    <professor id="5802">
        <name>fiGGILeU</name>
        <birthDate>9/12/2012</birthDate>
        <telephone>37288468</telephone>
        <address>MvKTxPcsCTmyOWeQ</address>
        <students>3625</students>
    </professor>
    <professor id="9125">
        <name>kEBKvvod</name>
        <birthDate>26/4/1990</birthDate>
        <telephone>00562679</telephone>
        <address>uemxHLsyRTLUbBEJ</address>
        <students>8584</students>
    </professor>
    <professor id="9440">
        <name>hjbzLNzu</name>
        <birthDate>13/7/1975</birthDate>
        <telephone>52330161</telephone>
        <address>nWepeYbMVGsxJOVt</address>
    </professor>
    <professor id="0615">
        <name>DbiuHGdf</name>
        <birthDate>25/1/1996</birthDate>
        <telephone>92115643</telephone>
        <address>ZXzlEOxbQNqjdxyT</address>
    </professor>
    <student id="0935">
        <name>HBQnBfxp</name>
        <telephone>95370946</telephone>
        <gender>Female</gender>
        <birthDate>29/1/2008</birthDate>
        <registrationDate>4/6/1978</registrationDate>
        <address>iCiroKBHhIAyMsvW</address>
    </student>
    <student id="4848">
        <name>mTLYIYLZ</name>
        <telephone>92349145</telephone>
        <gender>Female</gender>
        <birthDate>28/9/2002</birthDate>
        <registrationDate>1/2/2020</registrationDate>
        <address>HsNFCYgsYHMekoEE</address>
        <professor>7136</professor>
    </student>
    <student id="3625">
        <name>eXEcNkqb</name>
        <telephone>76472973</telephone>
        <gender>Other</gender>
        <birthDate>30/7/1982</birthDate>
        <registrationDate>25/5/1985</registrationDate>
        <address>EkAEKYlbtmSDGroF</address>
        <professor>5802</professor>
    </student>
    <student id="8316">
        <name>mbgORRUV</name>
        <telephone>06476639</telephone>
        <gender>Female</gender>
        <birthDate>2/6/1981</birthDate>
        <registrationDate>19/3/1973</registrationDate>
        <address>nHFMRNtgOMzWJPLZ</address>
        <professor>0253</professor>
    </student>
    <student id="4198">
        <name>uySUyLdi</name>
        <telephone>26870045</telephone>
        <gender>Male</gender>
        <birthDate>19/4/1972</birthDate>
        <registrationDate>17/5/1998</registrationDate>
        <address>iknuFmLRHBJxceUr</address>
        <professor>8309</professor>
    </student>
    <student id="8584">
        <name>oMfjfmJW</name>
        <telephone>20818747</telephone>
        <gender>Female</gender>
        <birthDate>13/8/1975</birthDate>
        <registrationDate>23/1/2011</registrationDate>
        <address>SVURIguVnOAiZHly</address>
        <professor>9125</professor>
    </student>
    <student id="1396">
        <name>aYaKUERA</name>
        <telephone>09072194</telephone>
        <gender>Female</gender>
        <birthDate>15/9/1992</birthDate>
        <registrationDate>30/1/1976</registrationDate>
        <address>VBnOsDYtyjyGUPoI</address>
    </student>
    <student id="7541">
        <name>ZoGtbBDQ</name>
        <telephone>22836190</telephone>
        <gender>Male</gender>
        <birthDate>27/3/2018</birthDate>
        <registrationDate>11/5/1989</registrationDate>
        <address>xeTFMtzmgpOxEWhP</address>
        <professor>9292</professor>
    </student>
    <student id="6583">
        <name>gxRnnjXu</name>
        <telephone>33335320</telephone>
        <gender>Male</gender>
        <birthDate>29/12/1987</birthDate>
        <registrationDate>8/5/2019</registrationDate>
        <address>OTbpzbuLLgjWxHun</address>
        <professor>8194</professor>
    </student>
    <student id="6935">
        <name>IgFQrlaa</name>
        <telephone>63725968</telephone>
        <gender>Female</gender>
        <birthDate>15/8/2004</birthDate>
        <registrationDate>21/2/1984</registrationDate>
        <address>JhUPrOXjoCZakpxc</address>
        <professor>9292</professor>
    </student>
</school>
